{
	"type": "minecraft:crafting_shapeless",
	"category": "misc",
	"group": "netherite_ingot",
	"ingredients": [
		"minecraft:netherite_scrap",
		"minecraft:netherite_scrap",
		"minecraft:netherite_scrap",
		"minecraft:netherite_scrap",
		"minecraft:iron_ingot",
		"minecraft:iron_ingot",
		"minecraft:iron_ingot",
		"minecraft:iron_ingot"
	],
	"result": {
		"id": "minecraft:wolf_spawn_egg",
		"count": 1,
		"components": {
			"minecraft:item_name": "Silversteel Ingot",
			"minecraft:enchantment_glint_override": false,
			"minecraft:entity_data": {
				"id": "minecraft:player"
			},
			"minecraft:item_model": "bracken:average_weapons/silversteel/ingot"
		}
	}
}